{
  "instrumentKey": "splendid_piano",
  "displayName": "Grand Piano (Splendid)",
  "baseUrl": "https://raw.githubusercontent.com/sfzinstruments/SplendidGrandPiano/master/Samples/",
  "ext": ".flac",
  "filePatterns": ["MF%20{NOTE}.flac", "Mf%20{NOTE}.flac"],
  "noteStyle": "sharp",
  "lowOct": 0,
  "highOct": 7,
  "transpose": 1,
  "decays": true,
  "vibrato": false,
  "releaseTime": 0.15,
  "volume": 1.0,
  "gateOpts": {},
  "comment": [
    "Splendid Grand Piano (sfzinstruments/SplendidGrandPiano on GitHub).",
    "MF velocity layer only. Filenames split between 'MF ' (uppercase,",
    "lower octaves) and 'Mf ' (mixed case, upper octaves) — filePatterns",
    "tries MF first then falls back to Mf. Space encoded as %20 in the",
    "pattern so the URL is RFC-valid and the per-sample `file` field",
    "round-trips at runtime. Generated by analyzer/generate-samples.js",
    "from splendid-piano.json."
  ]
}
